{
  "伊東園ホテル_2026-07-25": {
    "hotel": "伊東園ホテル",
    "date": "2026-07-25",
    "available": false,
    "raw_mark": "不明",
    "screenshot": "/home/runner/work/itoen-watcher/itoen-watcher/screenshots/伊東園ホテル_2026-07-25.png"
  },
  "伊東園ホテル別館_2026-07-25": {
    "hotel": "伊東園ホテル別館",
    "date": "2026-07-25",
    "available": false,
    "raw_mark": "不明",
    "screenshot": "/home/runner/work/itoen-watcher/itoen-watcher/screenshots/伊東園ホテル別館_2026-07-25.png"
  },
  "伊東園ホテル松川館_2026-07-25": {
    "hotel": "伊東園ホテル松川館",
    "date": "2026-07-25",
    "available": false,
    "raw_mark": "不明",
    "screenshot": "/home/runner/work/itoen-watcher/itoen-watcher/screenshots/伊東園ホテル松川館_2026-07-25.png"
  }
}